sourcemix_sdk/__init__.py
sourcemix_sdk/client.py
sourcemix_sdk-0.2.0.dist-info/METADATA
sourcemix_sdk-0.2.0.dist-info/WHEEL
sourcemix_sdk-0.2.0.dist-info/top_level.txt
sourcemix_sdk-0.2.0.dist-info/RECORD
