Metadata-Version: 2.4
Name: sourcemix-sdk
Version: 0.2.0
Summary: SDK for interacting with SourceMix agents
Author-email: Ferdinand Messens <ferdinandmessens@gmail.com>
License: MIT
Requires-Python: >=3.7
Requires-Dist: requests
